<?xml version="1.0" encoding="Windows-1252"?>
<Waveform xmlns:xsi="http://www.w3.org/2001/XMLSchema-instance" xmlns:xsd="http://www.w3.org/2001/XMLSchema">
  <signal>ecg</signal>
  <mode>vtach2</mode>
  <rangeMin>0</rangeMin>
  <rangeMax>140</rangeMax>
  <normalRate>60</normalRate>
  <cycles>1</cycles>
  <samples>374</samples>
  <data>
    <float>0.6096154</float>
    <float>0.601923048</float>
    <float>0.5942308</float>
    <float>0.5871795</float>
    <float>0.578846157</float>
    <float>0.5711538</float>
    <float>0.563461542</float>
    <float>0.5557692</float>
    <float>0.5480769</float>
    <float>0.5403846</float>
    <float>0.532051265</float>
    <float>0.524359</float>
    <float>0.516666651</float>
    <float>0.5083333</float>
    <float>0.501282036</float>
    <float>0.4929487</float>
    <float>0.4852564</float>
    <float>0.4775641</float>
    <float>0.4705128</float>
    <float>0.4628205</float>
    <float>0.455769241</float>
    <float>0.448076934</float>
    <float>0.439743578</float>
    <float>0.432692319</float>
    <float>0.42564103</float>
    <float>0.417948723</float>
    <float>0.410897434</float>
    <float>0.403205127</float>
    <float>0.396153837</float>
    <float>0.389102578</float>
    <float>0.381410271</float>
    <float>0.374358982</float>
    <float>0.366666675</float>
    <float>0.360897422</float>
    <float>0.3532051</float>
    <float>0.346153855</float>
    <float>0.339743584</float>
    <float>0.332051277</float>
    <float>0.325641036</float>
    <float>0.319230765</float>
    <float>0.312179476</float>
    <float>0.305769235</float>
    <float>0.298717946</float>
    <float>0.2923077</float>
    <float>0.285256416</float>
    <float>0.278846145</float>
    <float>0.2724359</float>
    <float>0.266025633</float>
    <float>0.2596154</float>
    <float>0.253846169</float>
    <float>0.248076916</float>
    <float>0.24166666</float>
    <float>0.2352564</float>
    <float>0.229487181</float>
    <float>0.223717943</float>
    <float>0.217307687</float>
    <float>0.211538464</float>
    <float>0.205769226</float>
    <float>0.2</float>
    <float>0.1948718</float>
    <float>0.188461542</float>
    <float>0.183333337</float>
    <float>0.178205132</float>
    <float>0.173076928</float>
    <float>0.16730769</float>
    <float>0.162179485</float>
    <float>0.15705128</float>
    <float>0.151923075</float>
    <float>0.14679487</float>
    <float>0.141666666</float>
    <float>0.136538461</float>
    <float>0.1326923</float>
    <float>0.1275641</float>
    <float>0.123076923</float>
    <float>0.118589744</float>
    <float>0.114102565</float>
    <float>0.109615386</float>
    <float>0.105128206</float>
    <float>0.100641027</float>
    <float>0.09679487</float>
    <float>0.0923076943</float>
    <float>0.08846154</float>
    <float>0.08461539</float>
    <float>0.08076923</float>
    <float>0.07692308</float>
    <float>0.0730769262</float>
    <float>0.06923077</float>
    <float>0.0660256445</float>
    <float>0.06282052</float>
    <float>0.0596153848</float>
    <float>0.05576923</float>
    <float>0.05320513</float>
    <float>0.0493589751</float>
    <float>0.0467948727</float>
    <float>0.04423077</float>
    <float>0.0403846167</float>
    <float>0.0378205143</float>
    <float>0.0352564119</float>
    <float>0.03269231</float>
    <float>0.03076923</float>
    <float>0.0282051284</float>
    <float>0.025641026</float>
    <float>0.0243589748</float>
    <float>0.0217948724</float>
    <float>0.01923077</float>
    <float>0.0179487187</float>
    <float>0.0160256419</float>
    <float>0.0141025642</float>
    <float>0.012820513</float>
    <float>0.0108974362</float>
    <float>0.009615385</float>
    <float>0.008333334</float>
    <float>0.007051282</float>
    <float>0.005769231</float>
    <float>0.00512820529</float>
    <float>0.00448717969</float>
    <float>0.00320512825</float>
    <float>0.00320512825</float>
    <float>0.00192307692</float>
    <float>0.00192307692</float>
    <float>0.00128205132</float>
    <float>0.00128205132</float>
    <float>0.00128205132</float>
    <float>0.000641025661</float>
    <float>0.00128205132</float>
    <float>0.00128205132</float>
    <float>0.00192307692</float>
    <float>0.00192307692</float>
    <float>0.00256410264</float>
    <float>0.00320512825</float>
    <float>0.00384615385</float>
    <float>0.00448717969</float>
    <float>0.005769231</float>
    <float>0.007051282</float>
    <float>0.007051282</float>
    <float>0.008333334</float>
    <float>0.0102564106</float>
    <float>0.0121794874</float>
    <float>0.0134615386</float>
    <float>0.01474359</float>
    <float>0.0166666675</float>
    <float>0.0185897443</float>
    <float>0.0205128212</float>
    <float>0.0230769236</float>
    <float>0.025</float>
    <float>0.0269230772</float>
    <float>0.02948718</float>
    <float>0.0320512839</float>
    <float>0.0346153863</float>
    <float>0.0378205143</float>
    <float>0.0403846167</float>
    <float>0.04294872</float>
    <float>0.0461538471</float>
    <float>0.0493589751</float>
    <float>0.0525641032</float>
    <float>0.05576923</float>
    <float>0.0596153848</float>
    <float>0.06282052</float>
    <float>0.06666667</float>
    <float>0.0705128238</float>
    <float>0.07435898</float>
    <float>0.07820513</float>
    <float>0.0820512846</float>
    <float>0.0865384638</float>
    <float>0.09038462</float>
    <float>0.0948718</float>
    <float>0.0993589759</float>
    <float>0.104487181</float>
    <float>0.108333334</float>
    <float>0.113461539</float>
    <float>0.118589744</float>
    <float>0.123076923</float>
    <float>0.1275641</float>
    <float>0.1326923</float>
    <float>0.137820512</float>
    <float>0.142948717</float>
    <float>0.148717955</float>
    <float>0.15384616</float>
    <float>0.159615383</float>
    <float>0.164102569</float>
    <float>0.170512825</float>
    <float>0.17564103</float>
    <float>0.180769235</float>
    <float>0.187179491</float>
    <float>0.1923077</float>
    <float>0.198717952</float>
    <float>0.203846157</float>
    <float>0.210256413</float>
    <float>0.215384617</float>
    <float>0.221794873</float>
    <float>0.2275641</float>
    <float>0.233974352</float>
    <float>0.23974359</float>
    <float>0.246153846</float>
    <float>0.251923084</float>
    <float>0.2576923</float>
    <float>0.264102578</float>
    <float>0.2698718</float>
    <float>0.276282042</float>
    <float>0.2820513</float>
    <float>0.287820518</float>
    <float>0.294230759</float>
    <float>0.3</float>
    <float>0.305128217</float>
    <float>0.311538458</float>
    <float>0.317948729</float>
    <float>0.323076934</float>
    <float>0.329487175</float>
    <float>0.33461538</float>
    <float>0.341025651</float>
    <float>0.346153855</float>
    <float>0.35128206</float>
    <float>0.3576923</float>
    <float>0.3628205</float>
    <float>0.3679487</float>
    <float>0.373076916</float>
    <float>0.378205121</float>
    <float>0.383333325</float>
    <float>0.38846153</float>
    <float>0.392948717</float>
    <float>0.398076922</float>
    <float>0.4025641</float>
    <float>0.4070513</float>
    <float>0.411538452</float>
    <float>0.416025639</float>
    <float>0.4198718</float>
    <float>0.423717946</float>
    <float>0.428205132</float>
    <float>0.431410253</float>
    <float>0.434615374</float>
    <float>0.438461542</float>
    <float>0.441666663</float>
    <float>0.444230765</float>
    <float>0.4474359</float>
    <float>0.450641036</float>
    <float>0.453205138</float>
    <float>0.455769241</float>
    <float>0.4576923</float>
    <float>0.4602564</float>
    <float>0.461538464</float>
    <float>0.463461548</float>
    <float>0.464743584</float>
    <float>0.466666669</float>
    <float>0.4679487</float>
    <float>0.468589753</float>
    <float>0.4698718</float>
    <float>0.4705128</float>
    <float>0.471153855</float>
    <float>0.471153855</float>
    <float>0.471153855</float>
    <float>0.471153855</float>
    <float>0.471153855</float>
    <float>0.4705128</float>
    <float>0.4698718</float>
    <float>0.4698718</float>
    <float>0.4698718</float>
    <float>0.471153855</float>
    <float>0.4724359</float>
    <float>0.473717958</float>
    <float>0.475641</float>
    <float>0.478846163</float>
    <float>0.482051283</float>
    <float>0.48653847</float>
    <float>0.491025627</float>
    <float>0.496153831</float>
    <float>0.5019231</float>
    <float>0.5089744</float>
    <float>0.516666651</float>
    <float>0.525</float>
    <float>0.533974349</float>
    <float>0.544230759</float>
    <float>0.5545788</float>
    <float>0.5660256</float>
    <float>0.578846157</float>
    <float>0.591666639</float>
    <float>0.6051282</float>
    <float>0.6198718</float>
    <float>0.6339744</float>
    <float>0.64928776</float>
    <float>0.664102554</float>
    <float>0.679487169</float>
    <float>0.694358945</float>
    <float>0.709041834</float>
    <float>0.725</float>
    <float>0.7397436</float>
    <float>0.754487157</float>
    <float>0.767948747</float>
    <float>0.7826923</float>
    <float>0.7955128</float>
    <float>0.807777762</float>
    <float>0.8198718</float>
    <float>0.8320513</float>
    <float>0.843491137</float>
    <float>0.853846133</float>
    <float>0.864102542</float>
    <float>0.873717964</float>
    <float>0.882692337</float>
    <float>0.8903846</float>
    <float>0.899359</float>
    <float>0.907051265</float>
    <float>0.9147436</float>
    <float>0.9217949</float>
    <float>0.928205132</float>
    <float>0.9339744</float>
    <float>0.9403846</float>
    <float>0.9461538</float>
    <float>0.951282</float>
    <float>0.955769241</float>
    <float>0.9602564</float>
    <float>0.9647436</float>
    <float>0.9685897</float>
    <float>0.9724359</float>
    <float>0.975641</float>
    <float>0.978846133</float>
    <float>0.981410265</float>
    <float>0.983974338</float>
    <float>0.9858974</float>
    <float>0.988461554</float>
    <float>0.9910256</float>
    <float>0.992307663</float>
    <float>0.994230747</float>
    <float>0.995512843</float>
    <float>0.9967949</float>
    <float>0.997435868</float>
    <float>0.9980769</float>
    <float>0.999358952</float>
    <float>0.999358952</float>
    <float>1</float>
    <float>1</float>
    <float>1</float>
    <float>0.999358952</float>
    <float>0.999358952</float>
    <float>0.998717964</float>
    <float>0.9980769</float>
    <float>0.9967949</float>
    <float>0.995512843</float>
    <float>0.993589759</float>
    <float>0.9910256</float>
    <float>0.989102542</float>
    <float>0.98653847</float>
    <float>0.983333349</float>
    <float>0.9801282</float>
    <float>0.97628206</float>
    <float>0.9724359</float>
    <float>0.9673077</float>
    <float>0.96282053</float>
    <float>0.9570513</float>
    <float>0.951282</float>
    <float>0.9442308</float>
    <float>0.9371795</float>
    <float>0.9301282</float>
    <float>0.9217949</float>
    <float>0.913461566</float>
    <float>0.903205156</float>
    <float>0.893589735</float>
    <float>0.882692337</float>
    <float>0.8717949</float>
    <float>0.8596154</float>
    <float>0.84807694</float>
    <float>0.835822</float>
    <float>0.8224359</float>
    <float>0.808333337</float>
    <float>0.7955128</float>
    <float>0.7807692</float>
    <float>0.766025662</float>
    <float>0.7507122</float>
    <float>0.7359649</float>
    <float>0.72307694</float>
    <float>0.7070513</float>
    <float>0.6935223</float>
    <float>0.678205132</float>
    <float>0.664102554</float>
    <float>0.649359</float>
    <float>0.6352564</float>
  </data>
</Waveform>